fitstools/__init__.py
fitstools/reader.py
fitstools/scripts/__init__.py
fitstools/scripts/cabs/__init__.py
fitstools/scripts/cabs/fitstools-base.yaml
fitstools/scripts/cabs/fitstools-stack.yaml
fitstoolz-0.0.1b1.dist-info/LICENSE
fitstoolz-0.0.1b1.dist-info/METADATA
fitstoolz-0.0.1b1.dist-info/WHEEL
fitstoolz-0.0.1b1.dist-info/RECORD
