Metadata-Version: 2.3
Name: fitstoolz
Version: 0.0.1b1
Summary: Python libraries for interfacing with FITS data in an intuitive way
License: MIT
Author: Sphesihle Makhathini, Mika Naidoo, Athanaseus Ramaila
Requires-Python: >=3.11,<3.13
Classifier: License :: OSI Approved :: MIT License
Classifier: Programming Language :: Python :: 3
Classifier: Programming Language :: Python :: 3.11
Classifier: Programming Language :: Python :: 3.12
Requires-Dist: astropy (>=7.1.0,<8.0.0)
Requires-Dist: dask-ms (==0.2.24)
Requires-Dist: numpy (>=2.0,<3.0)
Requires-Dist: stimela (>=2.1.2,<3.0.0)
Requires-Dist: xarray
Requires-Dist: zarr
